xk6_output_plugin_py/__init__.py
xk6_output_plugin_py/output.proto
xk6_output_plugin_py/output.py
xk6_output_plugin_py/output_pb2.py
xk6_output_plugin_py/output_pb2_grpc.py
xk6_output_plugin_py-0.1.0.dist-info/LICENSE
xk6_output_plugin_py-0.1.0.dist-info/METADATA
xk6_output_plugin_py-0.1.0.dist-info/WHEEL
xk6_output_plugin_py-0.1.0.dist-info/RECORD
