Metadata-Version: 2.1
Name: xk6-output-plugin-py
Version: 0.1.0
Summary: xk6-output-plugin Python API
Home-page: https://github.com/szkiba/xk6-output-plugin-py
Author: Ivan SZKIBA
Author-email: szkiba@users.noreply.github.com
Requires-Python: >=3.10,<4.0
Classifier: Programming Language :: Python :: 3
Classifier: Programming Language :: Python :: 3.10
Classifier: Programming Language :: Python :: 3.11
Requires-Dist: grpcio (>=1.54.2,<2.0.0)
Requires-Dist: grpcio-health-checking (>=1.54.2,<2.0.0)
Requires-Dist: python-json-logger (>=2.0.7,<3.0.0)
Project-URL: Repository, https://github.com/szkiba/xk6-output-plugin-py
